reactome_stats/__init__.py
reactome_stats/analysis.py
reactome_stats/goc.py
reactome_stats/kegg.py
reactome_stats/reactomegraphdb.py
reactome_stats/uniprot.py
reactome_stats-0.5.2.dist-info/DESCRIPTION.rst
reactome_stats-0.5.2.dist-info/METADATA
reactome_stats-0.5.2.dist-info/RECORD
reactome_stats-0.5.2.dist-info/WHEEL
reactome_stats-0.5.2.dist-info/metadata.json
reactome_stats-0.5.2.dist-info/top_level.txt
tests/__init__.py
tests/analysis.py
tests/goc.py
tests/kegg.py
tests/reactomegraphdb.py
tests/test_reactome_stats.py
tests/uniprot.py
