Metadata-Version: 2.0
Name: reactome-stats
Version: 0.5.2
Summary: Reactome Metrics and Coverage
Home-page: https://github.com/corinabioinformatic/Neo4J_at_Reactome/tree/ReactomeStats
Author: CorinaBioinformatic
Author-email: corina.bioinformatic@gmail.com
License: GNU GPLv3
Keywords: reactome pathways metrics kegg uniprot GOC
Platform: UNKNOWN
Requires-Python: ==2.7.*
Requires-Dist: pandas
Requires-Dist: neo4j-driver
Requires-Dist: matplotlib-venn
